huaweicloudsdkeg/__init__.py
huaweicloudsdkeg/v1/__init__.py
huaweicloudsdkeg/v1/eg_async_client.py
huaweicloudsdkeg/v1/eg_client.py
huaweicloudsdkeg/v1/model/__init__.py
huaweicloudsdkeg/v1/model/agency_create_req.py
huaweicloudsdkeg/v1/model/api_versions_links.py
huaweicloudsdkeg/v1/model/api_versions_versions.py
huaweicloudsdkeg/v1/model/apigw_target_detail.py
huaweicloudsdkeg/v1/model/batch_window.py
huaweicloudsdkeg/v1/model/catalog_target_info.py
huaweicloudsdkeg/v1/model/channel_create_req.py
huaweicloudsdkeg/v1/model/channel_create_req_policy.py
huaweicloudsdkeg/v1/model/channel_create_req_principal.py
huaweicloudsdkeg/v1/model/channel_info.py
huaweicloudsdkeg/v1/model/channel_update_req.py
huaweicloudsdkeg/v1/model/check_put_events_req.py
huaweicloudsdkeg/v1/model/check_put_events_req_sources.py
huaweicloudsdkeg/v1/model/check_put_events_request.py
huaweicloudsdkeg/v1/model/check_put_events_response.py
huaweicloudsdkeg/v1/model/check_put_events_result.py
huaweicloudsdkeg/v1/model/cloud_events.py
huaweicloudsdkeg/v1/model/connection_create_req.py
huaweicloudsdkeg/v1/model/connection_info.py
huaweicloudsdkeg/v1/model/connection_info_flavor.py
huaweicloudsdkeg/v1/model/connection_type.py
huaweicloudsdkeg/v1/model/connection_update_req.py
huaweicloudsdkeg/v1/model/create_agencies_request.py
huaweicloudsdkeg/v1/model/create_agencies_response.py
huaweicloudsdkeg/v1/model/create_channel_request.py
huaweicloudsdkeg/v1/model/create_channel_response.py
huaweicloudsdkeg/v1/model/create_connection_request.py
huaweicloudsdkeg/v1/model/create_connection_response.py
huaweicloudsdkeg/v1/model/create_endpoint_request.py
huaweicloudsdkeg/v1/model/create_endpoint_response.py
huaweicloudsdkeg/v1/model/create_event_schema_request.py
huaweicloudsdkeg/v1/model/create_event_schema_response.py
huaweicloudsdkeg/v1/model/create_event_schema_version_request.py
huaweicloudsdkeg/v1/model/create_event_schema_version_response.py
huaweicloudsdkeg/v1/model/create_event_source_request.py
huaweicloudsdkeg-3.1.184.dist-info/METADATA
huaweicloudsdkeg-3.1.184.dist-info/WHEEL
huaweicloudsdkeg-3.1.184.dist-info/licenses/LICENSE
huaweicloudsdkeg-3.1.184.dist-info/RECORD
